.gitignore
CITATION.cff
LICENSE
LICENSE_xtcocotools
MANIFEST.in
Makefile
README.md
pyproject.toml
requirements.txt
setup.cfg
setup.py
./common/maskApi.c
.github/workflows/publish-to-pypi.yml
annotations/example_coco_preds.json
annotations/example_coco_val.json
annotations/example_cropcoco_preds.json
annotations/example_cropcoco_val.json
annotations/example_crowdpose_preds.json
annotations/example_crowdpose_val.json
annotations/example_wholebody_preds.json
annotations/example_wholebody_val.json
assets/exoks_scheme.png
assets/visibility_levels.png
common/gason.cpp
common/gason.h
common/maskApi.c
common/maskApi.h
demos/demo_coco.py
demos/demo_coco_wholebody.py
demos/demo_cropcoco.py
demos/demo_crowdpose.py
exococotools/__init__.py
exococotools/_mask.c
exococotools/_mask.pyx
exococotools/coco.py
exococotools/cocoeval.py
exococotools/mask.py
exococotools/version.py
exococotools.egg-info/PKG-INFO
exococotools.egg-info/SOURCES.txt
exococotools.egg-info/dependency_links.txt
exococotools.egg-info/top_level.txt