Metadata-Version: 2.1
Name: exococotools
Version: 1.0.0
Summary: Extended OKS on top of xtcocotools
Home-page: https://github.com/MiraPurkrabek/exococotools
Author: Miroslav Purkrabek
Author-email: Miroslav Purkrabek <mira.purkrabek@gmail.com>
Maintainer-email: Miroslav Purkrabek <mira.purkrabek@gmail.com>
License: GPLv3
Classifier: Development Status :: 4 - Beta
Classifier: Programming Language :: Python
Requires-Python: >=3.7
License-File: LICENSE
